TEx/README.md
TEx/__init__.py
TEx/__main__.py
TEx/config.ini
TEx/core/__init__.py
TEx/core/base_module.py
TEx/core/dir_manager.py
TEx/core/mapper/__init__.py
TEx/core/mapper/keep_alive_entity_mapper.py
TEx/core/mapper/telethon_channel_mapper.py
TEx/core/mapper/telethon_message_mapper.py
TEx/core/mapper/telethon_user_mapper.py
TEx/core/media_download_handling/__init__.py
TEx/core/media_download_handling/do_nothing_media_downloader.py
TEx/core/media_download_handling/photo_media_downloader.py
TEx/core/media_download_handling/std_media_downloader.py
TEx/core/media_handler.py
TEx/core/media_metadata_handling/__init__.py
TEx/core/media_metadata_handling/do_nothing_media_handler.py
TEx/core/media_metadata_handling/generic_binary_handler.py
TEx/core/media_metadata_handling/geo_handler.py
TEx/core/media_metadata_handling/mp4_handler.py
TEx/core/media_metadata_handling/pdf_handler.py
TEx/core/media_metadata_handling/photo_handler.py
TEx/core/media_metadata_handling/sticker_handler.py
TEx/core/media_metadata_handling/text_handler.py
TEx/core/media_metadata_handling/webimage_handler.py
TEx/core/ocr/__init__.py
TEx/core/ocr/dummy_ocr_engine.py
TEx/core/ocr/ocr_engine_base.py
TEx/core/ocr/ocr_engine_factory.py
TEx/core/ocr/tesseract_ocr_engine.py
TEx/core/state_file.py
TEx/core/temp_file.py
TEx/database/__init__.py
TEx/database/db_initializer.py
TEx/database/db_manager.py
TEx/database/db_migration.py
TEx/database/telegram_group_database.py
TEx/exporter/__init__.py
TEx/exporter/exporter_base.py
TEx/exporter/exporter_engine.py
TEx/exporter/pandas_rolling_exporter.py
TEx/finder/__init__.py
TEx/finder/all_messages_finder.py
TEx/finder/base_finder.py
TEx/finder/finder_engine.py
TEx/finder/regex_finder.py
TEx/logging.conf
TEx/models/__init__.py
TEx/models/database/__init__.py
TEx/models/database/telegram_db_model.py
TEx/models/database/temp_db_models.py
TEx/models/facade/__init__.py
TEx/models/facade/finder_notification_facade_entity.py
telegramexplorer-0.3.0.dist-info/LICENSE
telegramexplorer-0.3.0.dist-info/METADATA
telegramexplorer-0.3.0.dist-info/WHEEL
telegramexplorer-0.3.0.dist-info/RECORD
