Metadata-Version: 2.1
Name: TelegramExplorer
Version: 0.3.0
Summary: Telegram Explorer
Home-page: https://github.com/guibacellar/TEx
License: Apache-2.0
Keywords: CyberSecurity,Investigation,OSINT,OpenSourceIntelligence,Tool
Author: Th3 0bservator
Author-email: th30bservator@gmail.com
Maintainer: Th3 0bservator
Maintainer-email: th30bservator@gmail.com
Requires-Python: >=3.8.1,<4.0
Classifier: Environment :: Console
Classifier: Intended Audience :: Information Technology
Classifier: License :: Freely Distributable
Classifier: License :: OSI Approved :: Apache Software License
Classifier: Natural Language :: English
Classifier: Operating System :: OS Independent
Classifier: Programming Language :: Python :: 3
Classifier: Programming Language :: Python :: 3.9
Classifier: Programming Language :: Python :: 3.10
Classifier: Programming Language :: Python :: 3.11
Classifier: Programming Language :: Python :: 3 :: Only
Classifier: Programming Language :: Python :: 3.8
Classifier: Topic :: Security
Classifier: Topic :: Software Development :: Build Tools
Classifier: Topic :: Software Development :: Libraries :: Python Modules
Classifier: Topic :: Utilities
Requires-Dist: Jinja2 (>=3.0.3)
Requires-Dist: SQLAlchemy (>=2.0.19,<2.1)
Requires-Dist: Telethon (==1.29.2)
Requires-Dist: aiofiles (==23.2.1)
Requires-Dist: aiosqlite (>=0.19.0)
Requires-Dist: async-timeout (==4.0.3)
Requires-Dist: build (>=0.10.0,<0.11.0)
Requires-Dist: cachetools (>=5.3.1,<6)
Requires-Dist: cryptg (>=0.2.post4)
Requires-Dist: discord-webhook[async] (>=1.3.0,<2)
Requires-Dist: elasticsearch[async] (==8.10.0)
Requires-Dist: poetry-core (>=1.6.1,<2)
Requires-Dist: poetry-plugin-export (>=1.4.0,<2.0.0)
Requires-Dist: pydantic (==2.4.2)
Requires-Dist: pytesseract (==0.3.10)
Requires-Dist: python-socks (==2.4.3)
Requires-Dist: pytz (>=2023.3)
Requires-Dist: requests (>=2.31.0,<3)
Requires-Dist: telethon-cryptg (>=0.0.4)
Requires-Dist: toml (>=0.10.2)
Requires-Dist: tox (>=4.10.0,<5.0.0)
Requires-Dist: types-aiofiles (==23.2.0.0)
Requires-Dist: urllib3 (>=1.26.8)
Project-URL: Documentation, https://telegramexplorer.readthedocs.io/en/latest/
Project-URL: Repository, https://github.com/guibacellar/TEx
